            <AUTO_ENDING_POSITION>
                <LEFT>
                    <STRAFE_RIGHT>
                        <distance>40.0</distance>
                        <velocity>0.5</velocity>
                    </STRAFE_RIGHT>
                </LEFT>
                <RIGHT>
                    <STRAFE_LEFT>
                        <distance>10.0</distance>
                        <velocity>0.5</velocity>
                    </STRAFE_LEFT>
                </RIGHT>
            </AUTO_ENDING_POSITION>